Lab1/incrementer.v
/*
 * Generated by Digital. Don't modify this file!
 * Any changes will be lost if this file is regenerated.
 */

module half_adder (
  input a,
  input b,
  output sum,
  output cry
);
  assign sum = (a ^ b);
  assign cry = (a & b);
endmodule

module incrementer (
  input [3:0] a,
  input inc,
  output cry,
  output [3:0] y
);
  wire s0;
  wire s1;
  wire s2;
  wire s3;
  wire s4;
  wire s5;
  wire s6;
  wire s7;
  wire s8;
  wire s9;
  wire s10;
  assign s0 = a[3];
  assign s3 = a[2];
  assign s6 = a[1];
  assign s9 = a[0];
  half_adder half_adder_i0 (
    .a( s9 ),
    .b( inc ),
    .sum( s10 ),
    .cry( s7 )
  );
  half_adder half_adder_i1 (
    .a( s6 ),
    .b( s7 ),
    .sum( s8 ),
    .cry( s4 )
  );
  half_adder half_adder_i2 (
    .a( s3 ),
    .b( s4 ),
    .sum( s5 ),
    .cry( s1 )
  );
  half_adder half_adder_i3 (
    .a( s0 ),
    .b( s1 ),
    .sum( s2 ),
    .cry( cry )
  );
  assign y[3] = s2;
  assign y[2] = s5;
  assign y[1] = s8;
  assign y[0] = s10;
endmodule

Lab1/incrementer_top.v
// Test module for lab 0
`timescale 1ns/1ns          // set a realistic time scale for the simulation

module incrementer_top();

reg [3:0]in_a;              // the a input to the circuit
reg inc;                    // the inc input to the circuit
wire [3:0] sum;             // the y output
wire cry;                   // the cry output

integer index;              // index into the input/output arrays
integer exp_out;            // expected output

initial    // all initial blocks run at start up...
begin
   inc = 1'b1;                                      // set the INC bit so it counts
   for ( index = 0 ; index < 16 ; index = index+1 ) // walk through the values
   begin
      in_a = index[3:0];            // the value to increment
      exp_out = index+1;            // the expected output value

      #10;                                // wait for propagation
      if ( sum != exp_out[3:0] )          // did we get what was expected?
         $display("Output mismatch when incrementing for\nentry ",index," expected ",
                  exp_out[3:0]," but got a sum of ",sum);
      if ( cry != exp_out[4] )            // did we get what was expected?
         $display("Output mismatch when incrementing for\nentry ",index," expected ",
                  exp_out[4]," but got a cry of ",cry);
   end

   inc = 1'b0;     // make sure it doesn't count...
   for ( index = 0 ; index < 3 ; index = index+1 ) // walk through the values
   begin
      in_a = index[3:0];            // the value to increment
      exp_out = in_a;               // the expected output value

      #10;                                // wait for propagation
      if ( sum != exp_out[3:0] )          // did we get what was expected?
         $display("Output mismatch when not incrementing for\nentry ",index," expected ",
                  exp_out[3:0]," but got a sum of ",sum);
      if ( cry != 1'b0 )                  // did we get what was expected?
         $display("Output mismatch when not incrementing for\nentry ",index," expected ",
                  exp_out[4]," but got a cry of ",cry);
   end

end

// this instantiates your design
incrementer incrementer(.a(in_a),.inc(inc),.y(sum),.cry(cry)); 

// dump the output to a VCD file so the waveform viewer can create the display
initial
begin
   $dumpfile("incrementer_waves.vcd"); // the name of the output file containing the waves
   $dumpvars(0,incrementer);           // 0 dumps all signals from incrementer down
end

endmodule

Lab1/incrementer_waves.vcd
$date
	Wed Aug 25 16:53:52 2021
$end
$version
	Icarus Verilog
$end
$timescale
	1ns
$end
$scope module incrementer_top $end
$scope module incrementer $end
$var wire 4 ! a [3:0] $end
$var wire 1 " inc $end
$var wire 4 # y [3:0] $end
$var wire 1 $ s9 $end
$var wire 1 % s8 $end
$var wire 1 & s7 $end
$var wire 1 ' s6 $end
$var wire 1 ( s5 $end
$var wire 1 ) s4 $end
$var wire 1 * s3 $end
$var wire 1 + s2 $end
$var wire 1 , s10 $end
$var wire 1 - s1 $end
$var wire 1 . s0 $end
$var wire 1 / cry $end
$scope module half_adder_i0 $end
$var wire 1 $ a $end
$var wire 1 " b $end
$var wire 1 & cry $end
$var wire 1 , sum $end
$upscope $end
$scope module half_adder_i1 $end
$var wire 1 ' a $end
$var wire 1 & b $end
$var wire 1 ) cry $end
$var wire 1 % sum $end
$upscope $end
$scope module half_adder_i2 $end
$var wire 1 * a $end
$var wire 1 ) b $end
$var wire 1 - cry $end
$var wire 1 ( sum $end
$upscope $end
$scope module half_adder_i3 $end
$var wire 1 . a $end
$var wire 1 - b $end
$var wire 1 / cry $end
$var wire 1 + sum $end
$upscope $end
$upscope $end
$upscope $end
$enddefinitions $end
#0
$dumpvars
0/
0.
0-
1,
0+
0*
0)
0(
0'
0&
0%
0$
b1 #
1"
b0 !
$end
#10
1%
b10 #
0,
1&
1$
b1 !
#20
b11 #
1,
0&
1'
0$
b10 !
#30
1(
0%
1)
b100 #
0,
1&
1$
b11 !
#40
0)
b101 #
1,
0&
1*
0'
0$
b100 !
#50
1%
b110 #
0,
1&
1$
b101 !
#60
b111 #
1,
0&
1'
0$
b110 !
#70
1+
0(
1-
0%
1)
b1000 #
0,
1&
1$
b111 !
#80
0-
0)
b1001 #
1,
0&
1.
0*
0'
0$
b1000 !
#90
1%
b1010 #
0,
1&
1$
b1001 !
#100
b1011 #
1,
0&
1'
0$
b1010 !
#110
1(
0%
1)
b1100 #
0,
1&
1$
b1011 !
#120
0)
b1101 #
1,
0&
1*
0'
0$
b1100 !
#130
1%
b1110 #
0,
1&
1$
b1101 !
#140
b1111 #
1,
0&
1'
0$
b1110 !
#150
0+
1/
0(
1-
0%
1)
b0 #
0,
1&
1$
b1111 !
#160
0/
0-
0)
0.
0*
0'
0$
b0 #
0,
0&
b0 !
0"
#170
b1 #
1,
1$
b1 !
#180
1%
b10 #
0,
1'
0$
b10 !
